[{"formatted_address": "Aeropuerto De Newark, Aeropuerto Internacional John F. Kennedy,New York, NY 11430,Estados Unidos, Jamaica, NY 11430, USA", "place_id": "ChIJj9-r5VtmwokRmdTNfrJkEwo", "address_components": [{"short_name": "Aeropuerto De Newark", "long_name": "Aeropuerto De Newark", "types": ["airport", "establishment", "point_of_interest"]}, {"short_name": "Jamaica", "long_name": "Jamaica", "types": ["neighborhood", "political"]}, {"short_name": "Queens", "long_name": "Queens", "types": ["political", "sublocality", "sublocality_level_1"]}, {"short_name": "Queens County", "long_name": "Queens County", "types": ["administrative_area_level_2", "political"]}, {"short_name": "NY", "long_name": "New York", "types": ["administrative_area_level_1", "political"]}, {"short_name": "US", "long_name": "United States", "types": ["country", "political"]}, {"short_name": "11430", "long_name": "11430", "types": ["postal_code"]}], "geometry": {"location_type": "APPROXIMATE", "location": {"lat": 40.6413111, "lng": -73.77813909999999}, "viewport": {"southwest": {"lat": 40.63996211970849, "lng": -73.7794880802915}, "northeast": {"lat": 40.64266008029149, "lng": -73.7767901197085}}}, "types": ["airport", "establishment", "point_of_interest"]}, {"formatted_address": "Perimeter Rd, Jamaica, NY 11430, USA", "place_id": "ChIJMzxEK1xmwokR3R4iYnF8KsU", "address_components": [{"short_name": "Perimeter Rd", "long_name": "Perimeter Road", "types": ["route"]}, {"short_name": "Jamaica", "long_name": "Jamaica", "types": ["neighborhood", "political"]}, {"short_name": "Queens", "long_name": "Queens", "types": ["political", "sublocality", "sublocality_level_1"]}, {"short_name": "Queens County", "long_name": "Queens County", "types": ["administrative_area_level_2", "political"]}, {"short_name": "NY", "long_name": "New York", "types": ["administrative_area_level_1", "political"]}, {"short_name": "US", "long_name": "United States", "types": ["country", "political"]}, {"short_name": "11430", "long_name": "11430", "types": ["postal_code"]}], "geometry": {"location_type": "GEOMETRIC_CENTER", "bounds": {"southwest": {"lat": 40.637576, "lng": -73.77698}, "northeast": {"lat": 40.6444055, "lng": -73.7716681}}, "location": {"lat": 40.6409891, "lng": -73.77432019999999}, "viewport": {"southwest": {"lat": 40.637576, "lng": -73.77698}, "northeast": {"lat": 40.6444055, "lng": -73.7716681}}}, "types": ["route"]}, {"formatted_address": "Queens, NY, USA", "place_id": "ChIJK1kKR2lDwokRBXtcbIvRCUE", "address_components": [{"short_name": "Queens", "long_name": "Queens", "types": ["political", "sublocality", "sublocality_level_1"]}, {"short_name": "New York", "long_name": "New York", "types": ["locality", "political"]}, {"short_name": "Queens County", "long_name": "Queens County", "types": ["administrative_area_level_2", "political"]}, {"short_name": "NY", "long_name": "New York", "types": ["administrative_area_level_1", "political"]}, {"short_name": "US", "long_name": "United States", "types": ["country", "political"]}], "geometry": {"location_type": "APPROXIMATE", "bounds": {"southwest": {"lat": 40.4897939, "lng": -74.0421119}, "northeast": {"lat": 40.8122421, "lng": -73.70027209999999}}, "location": {"lat": 40.7282239, "lng": -73.7948516}, "viewport": {"southwest": {"lat": 40.4897939, "lng": -74.0421119}, "northeast": {"lat": 40.8122421, "lng": -73.70027209999999}}}, "types": ["political", "sublocality", "sublocality_level_1"]}, {"formatted_address": "New York, NY, USA", "place_id": "ChIJOwg_06VPwokRYv534QaPC8g", "address_components": [{"short_name": "New York", "long_name": "New York", "types": ["locality", "political"]}, {"short_name": "NY", "long_name": "New York", "types": ["administrative_area_level_1", "political"]}, {"short_name": "US", "long_name": "United States", "types": ["country", "political"]}], "geometry": {"location_type": "APPROXIMATE", "bounds": {"southwest": {"lat": 40.4773991, "lng": -74.25908989999999}, "northeast": {"lat": 40.9175771, "lng": -73.70027209999999}}, "location": {"lat": 40.7127837, "lng": -74.0059413}, "viewport": {"southwest": {"lat": 40.4960439, "lng": -74.2557349}, "northeast": {"lat": 40.9152555, "lng": -73.70027209999999}}}, "types": ["locality", "political"]}, {"formatted_address": "Jamaica, NY 11430, USA", "place_id": "ChIJ9Zu3mBdmwokRWBjZr0Pt-QU", "address_components": [{"short_name": "11430", "long_name": "11430", "types": ["postal_code"]}, {"short_name": "Jamaica", "long_name": "Jamaica", "types": ["neighborhood", "political"]}, {"short_name": "Queens", "long_name": "Queens", "types": ["political", "sublocality", "sublocality_level_1"]}, {"short_name": "Queens County", "long_name": "Queens County", "types": ["administrative_area_level_2", "political"]}, {"short_name": "NY", "long_name": "New York", "types": ["administrative_area_level_1", "political"]}, {"short_name": "US", "long_name": "United States", "types": ["country", "political"]}], "geometry": {"location_type": "APPROXIMATE", "bounds": {"southwest": {"lat": 40.61618379999999, "lng": -73.8332159}, "northeast": {"lat": 40.66708, "lng": -73.7461079}}, "location": {"lat": 40.6433507, "lng": -73.7889689}, "viewport": {"southwest": {"lat": 40.61618379999999, "lng": -73.8332159}, "northeast": {"lat": 40.66708, "lng": -73.7461079}}}, "types": ["postal_code"]}, {"formatted_address": "Queens County, NY, USA", "place_id": "ChIJgav5pFbxwokRno6Tc5x2GL8", "address_components": [{"short_name": "Queens County", "long_name": "Queens County", "types": ["administrative_area_level_2", "political"]}, {"short_name": "NY", "long_name": "New York", "types": ["administrative_area_level_1", "political"]}, {"short_name": "US", "long_name": "United States", "types": ["country", "political"]}], "geometry": {"location_type": "APPROXIMATE", "bounds": {"southwest": {"lat": 40.4897939, "lng": -74.0421119}, "northeast": {"lat": 40.8122421, "lng": -73.70027209999999}}, "location": {"lat": 40.7282239, "lng": -73.7948516}, "viewport": {"southwest": {"lat": 40.5429789, "lng": -73.9626165}, "northeast": {"lat": 40.8007599, "lng": -73.70027209999999}}}, "types": ["administrative_area_level_2", "political"]}, {"formatted_address": "New York-Northern New Jersey-Long Island, NY-NJ-PA, USA", "place_id": "ChIJ3YJV4PRWwokRFFI21ZrHXtQ", "address_components": [{"short_name": "New York-Northern New Jersey-Long Island, NY-NJ-PA", "long_name": "New York-Northern New Jersey-Long Island, NY-NJ-PA", "types": ["political"]}, {"short_name": "US", "long_name": "United States", "types": ["country", "political"]}], "geometry": {"location_type": "APPROXIMATE", "bounds": {"southwest": {"lat": 39.49853299999999, "lng": -75.3585939}, "northeast": {"lat": 41.6018065, "lng": -71.856214}}, "location": {"lat": 40.9590293, "lng": -74.0300122}, "viewport": {"southwest": {"lat": 39.49853299999999, "lng": -75.3585939}, "northeast": {"lat": 41.6018065, "lng": -71.856214}}}, "types": ["political"]}, {"formatted_address": "New York Metropolitan Area, USA", "place_id": "ChIJ-5Z24NaGwokRiMh4Rj8FNMo", "address_components": [{"short_name": "New York Metropolitan Area", "long_name": "New York Metropolitan Area", "types": ["political"]}, {"short_name": "US", "long_name": "United States", "types": ["country", "political"]}], "geometry": {"location_type": "APPROXIMATE", "bounds": {"southwest": {"lat": 39.475198, "lng": -75.3587649}, "northeast": {"lat": 42.0809059, "lng": -71.777491}}, "location": {"lat": 40.7127761, "lng": -74.0059544}, "viewport": {"southwest": {"lat": 39.475198, "lng": -75.3587649}, "northeast": {"lat": 42.0809059, "lng": -71.777491}}}, "types": ["political"]}, {"formatted_address": "New York, USA", "place_id": "ChIJqaUj8fBLzEwRZ5UY3sHGz90", "address_components": [{"short_name": "NY", "long_name": "New York", "types": ["administrative_area_level_1", "establishment", "point_of_interest", "political"]}, {"short_name": "US", "long_name": "United States", "types": ["country", "political"]}], "geometry": {"location_type": "APPROXIMATE", "bounds": {"southwest": {"lat": 40.4773991, "lng": -79.7625901}, "northeast": {"lat": 45.015865, "lng": -71.777491}}, "location": {"lat": 43.2994285, "lng": -74.21793260000001}, "viewport": {"southwest": {"lat": 40.4961036, "lng": -79.761996}, "northeast": {"lat": 45.0125923, "lng": -71.8562029}}}, "types": ["administrative_area_level_1", "establishment", "point_of_interest", "political"]}, {"formatted_address": "United States", "place_id": "ChIJCzYy5IS16lQRQrfeQ5K5Oxw", "address_components": [{"short_name": "US", "long_name": "United States", "types": ["country", "political"]}], "geometry": {"location_type": "APPROXIMATE", "bounds": {"southwest": {"lat": 18.7763, "lng": 170.5957}, "northeast": {"lat": 71.5388001, "lng": -66.885417}}, "location": {"lat": 37.09024, "lng": -95.712891}, "viewport": {"southwest": {"lat": 25.82, "lng": -124.39}, "northeast": {"lat": 49.38, "lng": -66.94}}}, "types": ["country", "political"]}]
